second task/Fast/alu_register.v
module alu_register #(
    parameter WIDTH = 8
) (
    input wire clk_i,
    input wire rst_i,
    input wire [WIDTH-1:0] first_i,
    input wire [WIDTH-1:0] second_i,
    input wire [2:0] opcode_i,
    output wire [WIDTH-1:0] result_o
);

reg [WIDTH-1:0] result_reg;
reg [WIDTH-1:0] alu_result;

always @(*) begin
    case(opcode_i)
        3'b000: alu_result = ~(first_i & second_i);
        3'b001: alu_result = first_i ^ second_i;
        3'b010: alu_result = first_i + second_i;
        3'b011: alu_result = $signed(first_i) >>> second_i;
        3'b100: alu_result = first_i | second_i;
        3'b101: alu_result = first_i << second_i;
        3'b110: alu_result = ~first_i;
        3'b111: alu_result = { {WIDTH-1{1'b0}}, (first_i < second_i) };
        default: alu_result = {WIDTH{1'b0}};
    endcase
end

always @(posedge clk_i) begin
    if (rst_i)
        result_reg <= {WIDTH{1'b0}};
    else
        result_reg <= alu_result;
end

assign result_o = result_reg;

endmodule

second task/Verilog files/Fast/alu_register_tb.v
`timescale 1ns/1ps

module tb_alu_register;
    parameter WIDTH = 8;
    reg clk, rst;
    reg [WIDTH-1:0] first, second;
    reg [2:0] opcode;
    wire [WIDTH-1:0] result;

    alu_register #(.WIDTH(WIDTH)) dut (
        .clk_i(clk),
        .rst_i(rst),
        .first_i(first),
        .second_i(second),
        .opcode_i(opcode),
        .result_o(result)
    );

    initial begin
        clk = 0;
        forever #5 clk = ~clk;
    end

    initial begin
        $dumpfile("dump.vcd");
        $dumpvars(0, tb_alu_register);
    end

    initial begin
        rst = 1;
        first = 0;
        second = 0;
        opcode = 0;
        #20;

        rst = 0;
        #10;


        opcode = 3'b000;
        first = 8'hFF;
        second = 8'hAA;
        #10;


        opcode = 3'b001;
        first = 8'hAA;
        second = 8'h55;
        #10;


        opcode = 3'b010;
        first = 8'h80;
        second = 8'h7F;
        #10;


        opcode = 3'b011;
        first = 8'h80;
        second = 3;
        #10;


        opcode = 3'b100;
        first = 8'h0F;
        second = 8'hF0;
        #10;


        opcode = 3'b101;
        first = 8'h01;
        second = 3;
        #10;


        opcode = 3'b110;
        first = 8'hAA;
        #10;


        opcode = 3'b111;
        first = 8'h10;
        second = 8'h20;
        #10;


        opcode = 3'b010;
        first = 8'hFF;
        second = 8'h01;
        #10;


        opcode = 3'b101;
        first = 8'h01;
        second = 9;
        #10;


        opcode = 3'b010;
        first = 8'h12;
        second = 8'h34;
        #20;

        $finish;
    end

endmodule

second task/Fast/dump.vcd
$date
	Tue Apr 01 00:45:19 2025
$end
$version
	Icarus Verilog
$end
$timescale
	1ps
$end
$scope module tb_alu_register $end
$var wire 8 ! result [7:0] $end
$var parameter 32 " WIDTH $end
$var reg 1 # clk $end
$var reg 8 $ first [7:0] $end
$var reg 3 % opcode [2:0] $end
$var reg 1 & rst $end
$var reg 8 ' second [7:0] $end
$scope module dut $end
$var wire 1 # clk_i $end
$var wire 8 ( first_i [7:0] $end
$var wire 3 ) opcode_i [2:0] $end
$var wire 8 * result_o [7:0] $end
$var wire 1 & rst_i $end
$var wire 8 + second_i [7:0] $end
$var parameter 32 , WIDTH $end
$var reg 8 - alu_result [7:0] $end
$var reg 8 . result_reg [7:0] $end
$upscope $end
$upscope $end
$enddefinitions $end
$comment Show the parameter values. $end
$dumpall
b1000 ,
b1000 "
$end
#0
$dumpvars
bx .
b11111111 -
b0 +
bx *
b0 )
b0 (
b0 '
1&
b0 %
b0 $
0#
bx !
$end
#5000
b0 !
b0 *
b0 .
1#
#10000
0#
#15000
1#
#20000
0#
0&
#25000
b11111111 !
b11111111 *
b11111111 .
1#
#30000
b1010101 -
0#
b10101010 '
b10101010 +
b11111111 $
b11111111 (
#35000
b1010101 !
b1010101 *
b1010101 .
1#
#40000
b11111111 -
0#
b1010101 '
b1010101 +
b10101010 $
b10101010 (
b1 %
b1 )
#45000
b11111111 !
b11111111 *
b11111111 .
1#
#50000
0#
b1111111 '
b1111111 +
b10000000 $
b10000000 (
b10 %
b10 )
#55000
1#
#60000
b11110000 -
0#
b11 '
b11 +
b11 %
b11 )
#65000
b11110000 !
b11110000 *
b11110000 .
1#
#70000
b11111111 -
0#
b11110000 '
b11110000 +
b1111 $
b1111 (
b100 %
b100 )
#75000
b11111111 !
b11111111 *
b11111111 .
1#
#80000
b1000 -
0#
b11 '
b11 +
b1 $
b1 (
b101 %
b101 )
#85000
b1000 !
b1000 *
b1000 .
1#
#90000
b1010101 -
0#
b10101010 $
b10101010 (
b110 %
b110 )
#95000
b1010101 !
b1010101 *
b1010101 .
1#
#100000
b1 -
0#
b100000 '
b100000 +
b10000 $
b10000 (
b111 %
b111 )
#105000
b1 !
b1 *
b1 .
1#
#110000
b0 -
0#
b1 '
b1 +
b11111111 $
b11111111 (
b10 %
b10 )
#115000
b0 !
b0 *
b0 .
1#
#120000
0#
b1001 '
b1001 +
b1 $
b1 (
b101 %
b101 )
#125000
1#
#130000
b1000110 -
0#
b110100 '
b110100 +
b10010 $
b10010 (
b10 %
b10 )
#135000
b1000110 !
b1000110 *
b1000110 .
1#
